texport/__init__.py
texport/__main__.py
texport/export_config.py
texport/exporter.py
texport/html/__init__.py
texport/html/animation.py
texport/html/audio.py
texport/html/avatar.py
texport/html/base.py
texport/html/contact.py
texport/html/document.py
texport/html/forward.py
texport/html/media.py
texport/html/message.py
texport/html/message_body.py
texport/html/photo.py
texport/html/poll.py
texport/html/reply.py
texport/html/sticker.py
texport/html/username.py
texport/html/utils.py
texport/html/video.py
texport/html/video_note.py
texport/html/voice.py
texport/main.py
texport/media.py
texport/media_downloader.py
texport/messages_preloader.py
texport/messages_saver.py
texport/progress_print.py
texport/resources.py
t_export-0.1.2.dist-info/LICENSE
t_export-0.1.2.dist-info/METADATA
t_export-0.1.2.dist-info/WHEEL
t_export-0.1.2.dist-info/entry_points.txt
t_export-0.1.2.dist-info/RECORD
